setup.cfg
setup.py
yt/__init__.py
yt.finance.egg-info/PKG-INFO
yt.finance.egg-info/SOURCES.txt
yt.finance.egg-info/dependency_links.txt
yt.finance.egg-info/top_level.txt
yt/finance/__init__.py
yt/finance/binomial.py
yt/finance/interest.py
yt/finance/lib.py